Workbook

Sheet Backlog
A1: Epic ID | B1: Epic Name | C1: Story ID | D1: User Story | E1: Acceptance Criteria | F1: Priority | G1: Points | H1: Release | I1: Status | J1: Assignee | K1: Sprint | L1: Start Date | M1: Due Date | N1: Notes
A2: 0 | B2: Discovery & Architecture Spikes | C2: SPIKE-1 | D2: As an engineering team, I want to decide between NestJS and FastAPI for the backend API, so that we commit to one technology stack before development starts. | E2: - Comparison against team skills, ecosystem, and performance needs is documented - Decision is approved by the tech lead and recorded in the architecture doc | F2: Must | G2: 2 | H2: Release 1 | I2: Not Started
A3: 0 | B3: Discovery & Architecture Spikes | C3: SPIKE-2 | D3: As an engineering team, I want to choose between Apache AGE and Neo4j for the graph database, so that the ingestion and retrieval layers can be built on a confirmed technology. | E3: - Trade-off analysis (cost, hosting, query language, team familiarity) is documented - Decision is recorded and shared with the team | F3: Must | G3: 3 | H3: Release 1 | I3: Not Started
A4: 0 | B4: Discovery & Architecture Spikes | C4: SPIKE-3 | D4: As an engineering team, I want to select a vector store (pgvector, Qdrant, or Weaviate), so that embeddings can be stored and queried efficiently. | E4: - Comparison of shortlisted options is documented - Decision aligns with the chosen graph DB and hosting strategy | F4: Must | G4: 3 | H4: Release 1 | I4: Not Started
A5: 0 | B5: Discovery & Architecture Spikes | C5: SPIKE-4 | D5: As an engineering team, I want to define the multi-tenant isolation strategy (row-level vs schema-level), so that tenant data isolation is designed correctly from day one. | E5: - Isolation approach is documented for both the graph DB and vector store - Approach is validated against the 'no cross-tenant access' requirement | F5: Must | G5: 3 | H5: Release 1 | I5: Not Started
A6: 0 | B6: Discovery & Architecture Spikes | C6: SPIKE-5 | D6: As a product owner, I want to confirm which LLM providers will be supported at launch, so that the LLM abstraction layer and BYOK feature can be scoped correctly. | E6: - List of supported providers (e.g., Anthropic, OpenAI) is approved - Decision documented in the architecture doc | F6: Must | G6: 2 | H6: Release 1 | I6: Not Started
A7: 0 | B7: Discovery & Architecture Spikes | C7: SPIKE-6 | D7: As a product owner, I want to define the billing model and quota structure, so that usage limits and monetization can be implemented consistently. | E7: - Pricing tiers and quota rules are documented - Model is validated with stakeholders | F7: Should | G7: 3 | H7: Release 1 | I7: Not Started
A8: 0 | B8: Discovery & Architecture Spikes | C8: SPIKE-7 | D8: As a product owner, I want to confirm the final SLA target for platform uptime, so that infrastructure and on-call plans can be sized accordingly. | E8: - SLA percentage is agreed upon (e.g., 99.5%) - SLA is documented and communicated to the team | F8: Should | G8: 2 | H8: Release 1 | I8: Not Started
A9: 0 | B9: Discovery & Architecture Spikes | C9: SPIKE-8 | D9: As a product owner, I want to define the data retention policy for documents and conversation history, so that the platform stays compliant and predictable in storage cost. | E9: - Retention periods for documents and chat history are documented - Deletion/archival mechanism is scoped | F9: Should | G9: 2 | H9: Release 1 | I9: Not Started
A10: 0 | B10: Discovery & Architecture Spikes | C10: SPIKE-9 | D10: As an engineering team, I want to define the monitoring and alerting strategy, so that the observability epic can be implemented against a clear plan. | E10: - Tooling (e.g., Prometheus/Grafana or a hosted alternative) is selected - Key metrics and alert thresholds are drafted | F10: Should | G10: 3 | H10: Release 1 | I10: Not Started
A11: 1 | B11: Tenant Onboarding & Authentication | C11: US-1.1 | D11: As a prospective tenant, I want to sign up for an account, so that I can start using the platform. | E11: - Sign-up validates email format and password strength - A new tenant record and isolated workspace are created on success - A confirmation email is sent | F11: Must | G11: 5 | H11: Release 1 | I11: Not Started
A12: 1 | B12: Tenant Onboarding & Authentication | C12: US-1.2 | D12: As a tenant admin, I want to log in securely to my account, so that I can access my dashboard. | E12: - Login uses JWT/OAuth2-based authentication - Invalid credentials show a generic error message - Sessions expire after a defined inactivity period | F12: Must | G12: 3 | H12: Release 1 | I12: Not Started
A13: 1 | B13: Tenant Onboarding & Authentication | C13: US-1.3 | D13: As a tenant admin, I want to go through a guided onboarding flow (self-service or by invitation), so that I can set up my chatbot with minimal friction. | E13: - Wizard covers account setup, first data source, and chatbot basics - Invitation-based onboarding pre-fills the relevant tenant context | F13: Should | G13: 5 | H13: Release 1 | I13: Not Started
... A55: 12 | B55: Documentation | C55: US-12.1 | D55: As a developer, I want architecture and integration documentation (API guide, widget integration guide, architecture overview), so that I can understand, integrate with, and extend the system. | E55: - Documentation covers API auth, endpoints, and the widget snippet - The architecture overview stays up to date with major changes | F55: Should | G55: 5 | H55: Release 3 | I55: Not Started

Sheet Dashboard
A1: GraphRAG Chatbot Platform — Progress Dashboard
A2: Live totals below are calculated from the Backlog sheet — just keep Status up to date.
A4: Overall Progress
A5: Total Story Points | B5: =SUM(Backlog!G2:G55) -> 346
A6: Completed Story Points | B6: =SUMIFS(Backlog!G2:G55,Backlog!I2:I55,"Done") -> 0
A7: % Complete (Points) | B7: =IFERROR(B6/B5,0) -> 0
A8: Total Stories | B8: =COUNTA(Backlog!C2:C55) -> 54
A9: Completed Stories | B9: =COUNTIFS(Backlog!I2:I55,"Done") -> 0
A10: In Progress | B10: =COUNTIFS(Backlog!I2:I55,"In Progress") -> 0
A11: Blocked | B11: =COUNTIFS(Backlog!I2:I55,"Blocked") -> 0
A12: Not Started | B12: =COUNTIFS(Backlog!I2:I55,"Not Started") -> 54
A14: Progress by Epic
A15: Epic | B15: Total Pts | C15: Done Pts | D15: % Complete | E15: Stories | F15: Done Stories
A16: 0. Discovery & Architecture Spikes | B16: =SUMIFS(Backlog!$G$2:$G$55,Backlog!$A$2:$A$55,"0") -> 23 | C16: =SUMIFS(Backlog!$G$2:$G$55,Backlog!$A$2:$A$55,"0",Backlog!$I$2:$I$55,"Done") -> 0 | D16: =IFERROR(C16/B16,0) -> 0 | E16: =COUNTIFS(Backlog!$A$2:$A$55,"0") -> 9 | F16: =COUNTIFS(Backlog!$A$2:$A$55,"0",Backlog!$I$2:$I$55,"Done") -> 0
A17: 1. Tenant Onboarding & Authentication | B17: =SUMIFS(Backlog!$G$2:$G$55,Backlog!$A$2:$A$55,"1") -> 18 | C17: =SUMIFS(Backlog!$G$2:$G$55,Backlog!$A$2:$A$55,"1",Backlog!$I$2:$I$55,"Done") -> 0 | D17: =IFERROR(C17/B17,0) -> 0 | E17: =COUNTIFS(Backlog!$A$2:$A$55,"1") -> 4 | F17: =COUNTIFS(Backlog!$A$2:$A$55,"1",Backlog!$I$2:$I$55,"Done") -> 0
A18: 2. Data Source Management & Ingestion Pipeline | B18: =SUMIFS(Backlog!$G$2:$G$55,Backlog!$A$2:$A$55,"2") -> 58 | C18: =SUMIFS(Backlog!$G$2:$G$55,Backlog!$A$2:$A$55,"2",Backlog!$I$2:$I$55,"Done") -> 0 | D18: =IFERROR(C18/B18,0) -> 0 | E18: =COUNTIFS(Backlog!$A$2:$A$55,"2") -> 8 | F18: =COUNTIFS(Backlog!$A$2:$A$55,"2",Backlog!$I$2:$I$55,"Done") -> 0
A19: 3. Chatbot Configuration & Personalization | B19: =SUMIFS(Backlog!$G$2:$G$55,Backlog!$A$2:$A$55,"3") -> 24 | C19: =SUMIFS(Backlog!$G$2:$G$55,Backlog!$A$2:$A$55,"3",Backlog!$I$2:$I$55,"Done") -> 0 | D19: =IFERROR(C19/B19,0) -> 0 | E19: =COUNTIFS(Backlog!$A$2:$A$55,"3") -> 4 | F19: =COUNTIFS(Backlog!$A$2:$A$55,"3",Backlog!$I$2:$I$55,"Done") -> 0
A20: 4. Public API & Developer Access | B20: =SUMIFS(Backlog!$G$2:$G$55,Backlog!$A$2:$A$55,"4") -> 55 | C20: =SUMIFS(Backlog!$G$2:$G$55,Backlog!$A$2:$A$55,"4",Backlog!$I$2:$I$55,"Done") -> 0 | D20: =IFERROR(C20/B20,0) -> 0 | E20: =COUNTIFS(Backlog!$A$2:$A$55,"4") -> 7 | F20: =COUNTIFS(Backlog!$A$2:$A$55,"4",Backlog!$I$2:$I$55,"Done") -> 0
A21: 5. Embeddable Micro-Frontend Widget | B21: =SUMIFS(Backlog!$G$2:$G$55,Backlog!$A$2:$A$55,"5") -> 26 | C21: =SUMIFS(Backlog!$G$2:$G$55,Backlog!$A$2:$A$55,"5",Backlog!$I$2:$I$55,"Done") -> 0 | D21: =IFERROR(C21/B21,0) -> 0 | E21: =COUNTIFS(Backlog!$A$2:$A$55,"5") -> 4 | F21: =COUNTIFS(Backlog!$A$2:$A$55,"5",Backlog!$I$2:$I$55,"Done") -> 0
A22: 6. Tenant Dashboard & Analytics | B22: =SUMIFS(Backlog!$G$2:$G$55,Backlog!$A$2:$A$55,"6") -> 21 | C22: =SUMIFS(Backlog!$G$2:$G$55,Backlog!$A$2:$A$55,"6",Backlog!$I$2:$I$55,"Done") -> 0 | D22: =IFERROR(C22/B22,0) -> 0 | E22: =COUNTIFS(Backlog!$A$2:$A$55,"6") -> 3 | F22: =COUNTIFS(Backlog!$A$2:$A$55,"6",Backlog!$I$2:$I$55,"Done") -> 0
A23: 7. Billing & Quotas | B23: =SUMIFS(Backlog!$G$2:$G$55,Backlog!$A$2:$A$55,"7") -> 13 | C23: =SUMIFS(Backlog!$G$2:$G$55,Backlog!$A$2:$A$55,"7",Backlog!$I$2:$I$55,"Done") -> 0 | D23: =IFERROR(C23/B23,0) -> 0 | E23: =COUNTIFS(Backlog!$A$2:$A$55,"7") -> 2 | F23: =COUNTIFS(Backlog!$A$2:$A$55,"7",Backlog!$I$2:$I$55,"Done") -> 0
A24: 8. Super Admin / Platform Administration | B24: =SUMIFS(Backlog!$G$2:$G$55,Backlog!$A$2:$A$55,"8") -> 21 | C24: =SUMIFS(Backlog!$G$2:$G$55,Backlog!$A$2:$A$55,"8",Backlog!$I$2:$I$55,"Done") -> 0 | D24: =IFERROR(C24/B24,0) -> 0 | E24: =COUNTIFS(Backlog!$A$2:$A$55,"8") -> 3 | F24: =COUNTIFS(Backlog!$A$2:$A$55,"8",Backlog!$I$2:$I$55,"Done") -> 0
A25: 9. Multi-Tenant Isolation & Security | B25: =SUMIFS(Backlog!$G$2:$G$55,Backlog!$A$2:$A$55,"9") -> 29 | C25: =SUMIFS(Backlog!$G$2:$G$55,Backlog!$A$2:$A$55,"9",Backlog!$I$2:$I$55,"Done") -> 0 | D25: =IFERROR(C25/B25,0) -> 0 | E25: =COUNTIFS(Backlog!$A$2:$A$55,"9") -> 3 | F25: =COUNTIFS(Backlog!$A$2:$A$55,"9",Backlog!$I$2:$I$55,"Done") -> 0
A26: 10. Scalability, Performance & Observability | B26: =SUMIFS(Backlog!$G$2:$G$55,Backlog!$A$2:$A$55,"10") -> 37 | C26: =SUMIFS(Backlog!$G$2:$G$55,Backlog!$A$2:$A$55,"10",Backlog!$I$2:$I$55,"Done") -> 0 | D26: =IFERROR(C26/B26,0) -> 0 | E26: =COUNTIFS(Backlog!$A$2:$A$55,"10") -> 4 | F26: =COUNTIFS(Backlog!$A$2:$A$55,"10",Backlog!$I$2:$I$55,"Done") -> 0
A27: 11. Infrastructure & Deployment | B27: =SUMIFS(Backlog!$G$2:$G$55,Backlog!$A$2:$A$55,"11") -> 16 | C27: =SUMIFS(Backlog!$G$2:$G$55,Backlog!$A$2:$A$55,"11",Backlog!$I$2:$I$55,"Done") -> 0 | D27: =IFERROR(C27/B27,0) -> 0 | E27: =COUNTIFS(Backlog!$A$2:$A$55,"11") -> 2 | F27: =COUNTIFS(Backlog!$A$2:$A$55,"11",Backlog!$I$2:$I$55,"Done") -> 0
A28: 12. Documentation | B28: =SUMIFS(Backlog!$G$2:$G$55,Backlog!$A$2:$A$55,"12") -> 5 | C28: =SUMIFS(Backlog!$G$2:$G$55,Backlog!$A$2:$A$55,"12",Backlog!$I$2:$I$55,"Done") -> 0 | D28: =IFERROR(C28/B28,0) -> 0 | E28: =COUNTIFS(Backlog!$A$2:$A$55,"12") -> 1 | F28: =COUNTIFS(Backlog!$A$2:$A$55,"12",Backlog!$I$2:$I$55,"Done") -> 0
A30: Progress by Priority
A31: Priority | B31: Total Pts | C31: Done Pts | D31: % Complete
A32: Must | B32: =SUMIFS(Backlog!$G$2:$G$55,Backlog!$F$2:$F$55,"Must") -> 205 | C32: =SUMIFS(Backlog!$G$2:$G$55,Backlog!$F$2:$F$55,"Must",Backlog!$I$2:$I$55,"Done") -> 0 | D32: =IFERROR(C32/B32,0) -> 0
A33: Should | B33: =SUMIFS(Backlog!$G$2:$G$55,Backlog!$F$2:$F$55,"Should") -> 117 | C33: =SUMIFS(Backlog!$G$2:$G$55,Backlog!$F$2:$F$55,"Should",Backlog!$I$2:$I$55,"Done") -> 0 | D33: =IFERROR(C33/B33,0) -> 0
A34: Could | B34: =SUMIFS(Backlog!$G$2:$G$55,Backlog!$F$2:$F$55,"Could") -> 24 | C34: =SUMIFS(Backlog!$G$2:$G$55,Backlog!$F$2:$F$55,"Could",Backlog!$I$2:$I$55,"Done") -> 0 | D34: =IFERROR(C34/B34,0) -> 0
A36: Story Status Breakdown
A37: Status | B37: Stories | C37: Points
A38: Not Started | B38: =COUNTIFS(Backlog!$I$2:$I$55,"Not Started") -> 54 | C38: =SUMIFS(Backlog!$G$2:$G$55,Backlog!$I$2:$I$55,"Not Started") -> 346
A39: In Progress | B39: =COUNTIFS(Backlog!$I$2:$I$55,"In Progress") -> 0 | C39: =SUMIFS(Backlog!$G$2:$G$55,Backlog!$I$2:$I$55,"In Progress") -> 0
A40: In Review | B40: =COUNTIFS(Backlog!$I$2:$I$55,"In Review") -> 0 | C40: =SUMIFS(Backlog!$G$2:$G$55,Backlog!$I$2:$I$55,"In Review") -> 0
A41: Blocked | B41: =COUNTIFS(Backlog!$I$2:$I$55,"Blocked") -> 0 | C41: =SUMIFS(Backlog!$G$2:$G$55,Backlog!$I$2:$I$55,"Blocked") -> 0
A42: Done | B42: =COUNTIFS(Backlog!$I$2:$I$55,"Done") -> 0 | C42: =SUMIFS(Backlog!$G$2:$G$55,Backlog!$I$2:$I$55,"Done") -> 0

Sheet How to use
A1: How to use this tracker
A3: 1. Backlog sheet
A4: This is the full product backlog (54 items across 13 epics), carried over from the product backlog document.
A5: Blue-gray headers (columns A-H) are the backlog definition — epic, story, acceptance criteria, priority, points, planned release. Leave these as-is.
A6: Orange headers (columns I-N) are for your team to fill in and update as work progresses: Status, Assignee, Sprint, Start Date, Due Date, Notes.
A7: Status is a dropdown: Not Started, In Progress, In Review, Blocked, Done. The cell colors automatically once you pick a value.
A8: Sprint is a dropdown (Backlog, Sprint 0-11) matching the release plan's suggested sprint ranges.
A9: Use the filter arrows on row 1 to view one epic, one assignee, or one status at a time.
A11: 2. Dashboard sheet
A12: Everything here is a live formula pulling from the Backlog sheet — it updates automatically as you change Status.
A13: Overall Progress: total points, completed points, and story counts by status.
A14: Progress by Epic / by Priority: where the team's effort stands, broken down two ways.
... A20: Check the Dashboard sheet in stand-ups or before a manager update — no manual counting needed.
